<annotation>
  <folder>input</folder>
  <filename>r2-1950.jpg</filename>
  <path>/Users/administrador/PycharmProjects/OpenLabeling/OpenLabeling/main/input/r2-1950.jpg</path>
  <source>
    <database>Unknown</database>
  </source>
  <size>
    <width>400</width>
    <height>400</height>
    <depth>3</depth>
  </size>
  <segmented>0</segmented>
  <object>
    <name>Robot</name>
    <pose>Unspecified</pose>
    <truncated>0</truncated>
    <difficult>0</difficult>
    <bndbox>
      <xmin>90</xmin>
      <ymin>137</ymin>
      <xmax>136</xmax>
      <ymax>217</ymax>
    </bndbox>
  </object>
  <object>
    <name>Ball</name>
    <pose>Unspecified</pose>
    <truncated>0</truncated>
    <difficult>0</difficult>
    <bndbox>
      <xmin>137</xmin>
      <ymin>152</ymin>
      <xmax>159</xmax>
      <ymax>189</ymax>
    </bndbox>
  </object>
</annotation>
